MPRACollection/MPRACollection.py
MPRACollection/__init__.py
MPRACollection/cli.py
MPRACollection/utils.py
MPRACollection-0.1.0.dist-info/LICENSE
MPRACollection-0.1.0.dist-info/METADATA
MPRACollection-0.1.0.dist-info/WHEEL
MPRACollection-0.1.0.dist-info/top_level.txt
MPRACollection-0.1.0.dist-info/RECORD
